{
	"_version": "1.1.0",
	"resources": [
		{
			"name": ".theming",
			"size": 90,
			"theme": "sap_horizon"
		},
		{
			"name": "AvatarGroup.less",
			"size": 886,
			"designtime": true,
			"theme": "sap_horizon"
		},
		{
			"name": "Card.less",
			"size": 1419,
			"designtime": true,
			"theme": "sap_horizon"
		},
		{
			"name": "DynamicPage.less",
			"size": 5480,
			"designtime": true,
			"theme": "sap_horizon"
		},
		{
			"name": "DynamicPageHeader.less",
			"size": 878,
			"designtime": true,
			"theme": "sap_horizon"
		},
		{
			"name": "DynamicPageTitle.less",
			"size": 4600,
			"designtime": true,
			"theme": "sap_horizon"
		},
		{
			"name": "FlexibleColumnLayout.less",
			"size": 1368,
			"designtime": true,
			"theme": "sap_horizon"
		},
		{
			"name": "GridList.less",
			"size": 399,
			"designtime": true,
			"theme": "sap_horizon"
		},
		{
			"name": "GridListItem.less",
			"size": 461,
			"designtime": true,
			"theme": "sap_horizon"
		},
		{
			"name": "ProductSwitchItem.less",
			"size": 187,
			"designtime": true,
			"theme": "sap_horizon"
		},
		{
			"name": "ShellBar.less",
			"size": 14198,
			"designtime": true,
			"theme": "sap_horizon"
		},
		{
			"name": "SidePanel.less",
			"size": 510,
			"designtime": true,
			"theme": "sap_horizon"
		},
		{
			"name": "css_variables.css",
			"size": 5051,
			"theme": "sap_horizon"
		},
		{
			"name": "css_variables.less",
			"size": 148009,
			"designtime": true,
			"theme": "sap_horizon"
		},
		{
			"name": "css_variables.source.less",
			"size": 147647,
			"designtime": true,
			"theme": "sap_horizon"
		},
		{
			"name": "library-RTL.css",
			"size": 126387,
			"theme": "sap_horizon"
		},
		{
			"name": "library-parameters.json",
			"module": "sap/f/themes/sap_horizon/library-parameters.json",
			"size": 2104,
			"theme": "sap_horizon"
		},
		{
			"name": "library.css",
			"size": 126399,
			"theme": "sap_horizon"
		},
		{
			"name": "library.less",
			"size": 31336,
			"designtime": true,
			"theme": "sap_horizon"
		},
		{
			"name": "library.source.less",
			"size": 607,
			"designtime": true,
			"theme": "sap_horizon"
		},
		{
			"name": "library_skeleton-RTL.css",
			"size": 130369,
			"theme": "sap_horizon"
		},
		{
			"name": "library_skeleton.css",
			"size": 130382,
			"theme": "sap_horizon"
		},
		{
			"name": "resources.json",
			"size": 2366
		}
	]
}